simple_msteams/__init__.py
simple_msteams/__main__.py
simple_msteams/client.py
simple_msteams-0.0.7.dist-info/METADATA
simple_msteams-0.0.7.dist-info/WHEEL
simple_msteams-0.0.7.dist-info/entry_points.txt
simple_msteams-0.0.7.dist-info/top_level.txt
simple_msteams-0.0.7.dist-info/RECORD
